latvian_names/__init__.py
latvian_names/cli.py
latvian_names/core.py
latvian_names/settings.py
lv_name_api-0.1.0.dist-info/METADATA
lv_name_api-0.1.0.dist-info/WHEEL
lv_name_api-0.1.0.dist-info/entry_points.txt
lv_name_api-0.1.0.dist-info/top_level.txt
lv_name_api-0.1.0.dist-info/RECORD
