Metadata-Version: 2.4
Name: lv-name-api
Version: 0.1.0
Summary: CLI for searching Latvian names from pmlp.gov.lv
Author: randomlatvian
License-Expression: MIT
Requires-Dist: requests
Requires-Dist: beautifulsoup4
Requires-Dist: prettytable
